{
  "signedContributors": [
    {
      "name": "mnvr",
      "id": 24503581,
      "comment_id": 1345920094,
      "created_at": "2022-12-12T05:42:03Z",
      "repoId": 577156537,
      "pullRequestNo": 1
    },
    {
      "name": "vishnukvmd",
      "id": 1161789,
      "comment_id": 1346045146,
      "created_at": "2022-12-12T08:04:59Z",
      "repoId": 560284721,
      "pullRequestNo": 10
    },
    {
      "name": "ua741",
      "id": 254676,
      "comment_id": 1346142623,
      "created_at": "2022-12-12T09:17:27Z",
      "repoId": 560284721,
      "pullRequestNo": 12
    }
  ]
}